pkg/__init__.py
pkg/pattern.py
Geometery_Patterns-0.1.0.dist-info/METADATA
Geometery_Patterns-0.1.0.dist-info/WHEEL
Geometery_Patterns-0.1.0.dist-info/top_level.txt
Geometery_Patterns-0.1.0.dist-info/RECORD
