Metadata-Version: 2.1
Name: Geometery_Patterns
Version: 0.1.0
Summary: Print Pattern Like Pyramid, Right Angle, and Left 
Home-page: https://github.com/prachikabra121/prachi-test-package
Author: Vivek Tomar
Author-email: vivek.tomar.data@gmail.com
Classifier: Programming Language :: Python :: 3
Classifier: License :: OSI Approved :: MIT License
Classifier: Operating System :: OS Independent
Requires-Python: >=3.6
